{
  "elements": [
    {
      "disabled": true,
      "name": "Node_9/ISField_3.2",
      "open_switches": []
    },
    {
      "disabled": true,
      "name": "Node_9/IS1.2",
      "open_switches": []
    },
    {
      "disabled": true,
      "name": "Node_9/ISField_2.3",
      "open_switches": []
    }
  ],
  "meta": {
    "case": "Industry_Park",
    "creator": "powerfactory-tools @ version 2.1.0",
    "date": "2024-05-23",
    "grid": "HV_9_Bus",
    "id": "dfc3fb48-2599-4bcc-bafc-ad82e0384fd7",
    "project": "PowerFactory-Tools",
    "sign_convention": "PASSIVE",
    "version": "2.2.0"
  }
}